Metadata-Version: 1.0
Name: ffmodeler
Version: 0.2
Summary: Farfield modeler
Home-page: UNKNOWN
Author: Sergio Barreto
Author-email: sergiobarreto@id.uff.br
License: UNKNOWN
Platform: UNKNOWN
